signalr_aio_wsclient/__init__.py
signalr_aio_wsclient/_connection.py
signalr_aio_wsclient/events/__init__.py
signalr_aio_wsclient/events/_events.py
signalr_aio_wsclient/hubs/__init__.py
signalr_aio_wsclient/hubs/_hub.py
signalr_aio_wsclient/transports/__init__.py
signalr_aio_wsclient/transports/_exceptions.py
signalr_aio_wsclient/transports/_parameters.py
signalr_aio_wsclient/transports/_queue_events.py
signalr_aio_wsclient/transports/_transport.py
wsclient/__init__.py
wsclient/base.py
wsclient/channel.py
wsclient/conn.py
wsclient/conn_mgr.py
wsclient/errors.py
wsclient/extend_attrs.py
wsclient/interpreter.py
wsclient/merged.py
wsclient/sub.py
wsclient/transport.py
wsclient/url.py
wsclient-0.4.0.dist-info/METADATA
wsclient-0.4.0.dist-info/WHEEL
wsclient-0.4.0.dist-info/top_level.txt
wsclient-0.4.0.dist-info/RECORD
